structures/__init__.py
structures/admin.py
structures/app_settings.py
structures/apps.py
structures/auth_hooks.py
structures/checks.py
structures/constants.py
structures/forms.py
structures/helpers.py
structures/managers.py
structures/providers.py
structures/tasks.py
structures/urls.py
structures/core/__init__.py
structures/core/notification_timers.py
structures/core/notification_types.py
structures/core/serializers.py
structures/core/sovereignty.py
structures/core/starbases.py
structures/core/notification_embeds/__init__.py
structures/core/notification_embeds/billing_embeds.py
structures/core/notification_embeds/corporate_embeds.py
structures/core/notification_embeds/helpers.py
structures/core/notification_embeds/main.py
structures/core/notification_embeds/moonmining_embeds.py
structures/core/notification_embeds/orbital_embeds.py
structures/core/notification_embeds/skyhook_embeds.py
structures/core/notification_embeds/sov_embeds.py
structures/core/notification_embeds/structures_embeds.py
structures/core/notification_embeds/tower_embeds.py
structures/core/notification_embeds/war_embeds.py
structures/locale/django.pot
structures/locale/de/LC_MESSAGES/django.mo
structures/locale/de/LC_MESSAGES/django.po
structures/locale/en/LC_MESSAGES/django.mo
structures/locale/en/LC_MESSAGES/django.po
structures/locale/es/LC_MESSAGES/django.mo
structures/locale/es/LC_MESSAGES/django.po
structures/locale/fr_FR/LC_MESSAGES/django.mo
structures/locale/fr_FR/LC_MESSAGES/django.po
structures/locale/it_IT/LC_MESSAGES/django.mo
structures/locale/it_IT/LC_MESSAGES/django.po
structures/locale/ja/LC_MESSAGES/django.mo
structures/locale/ja/LC_MESSAGES/django.po
structures/locale/ko_KR/LC_MESSAGES/django.mo
structures/locale/ko_KR/LC_MESSAGES/django.po
structures/locale/ru/LC_MESSAGES/django.mo
structures/locale/ru/LC_MESSAGES/django.po
structures/locale/uk/LC_MESSAGES/django.mo
structures/locale/uk/LC_MESSAGES/django.po
structures/locale/zh_Hans/LC_MESSAGES/django.mo
aa_structures-3.3.1.dist-info/licenses/LICENSE
aa_structures-3.3.1.dist-info/WHEEL
aa_structures-3.3.1.dist-info/METADATA
aa_structures-3.3.1.dist-info/RECORD
