Metadata-Version: 2.4
Name: aa-structures
Version: 3.3.1
Summary: App for managing Eve Online structures with Alliance Auth.
Author-email: Erik Kalkoken <kalkoken87@gmail.com>
Requires-Python: >=3.8
Classifier: Environment :: Web Environment
Classifier: Framework :: Django
Classifier: Framework :: Django :: 4.2
Classifier: Intended Audience :: End Users/Desktop
Classifier: License :: OSI Approved :: MIT License
Classifier: Operating System :: OS Independent
Classifier: Programming Language :: Python
Classifier: Programming Language :: Python :: 3.8
Classifier: Programming Language :: Python :: 3.9
Classifier: Programming Language :: Python :: 3.10
Classifier: Programming Language :: Python :: 3.11
Classifier: Programming Language :: Python :: 3.12
Classifier: Topic :: Internet :: WWW/HTTP
Classifier: Topic :: Internet :: WWW/HTTP :: Dynamic Content
License-File: LICENSE
Requires-Dist: allianceauth-app-utils>=1.29.1
Requires-Dist: allianceauth>=4,<5
Requires-Dist: dhooks-lite>=1.0
Requires-Dist: django-eveuniverse>=1.6
Requires-Dist: django-multiselectfield
Requires-Dist: django-navhelper
Requires-Dist: pytz!=2022.2
Requires-Dist: redis-simple-mq>=1.1
Requires-Dist: humanize>=4.7
Project-URL: Changelog, https://gitlab.com/ErikKalkoken/aa-structures/-/blob/master/CHANGELOG.md
Project-URL: Documentation, https://aa-structures.readthedocs.io/en/latest/
Project-URL: Homepage, https://gitlab.com/ErikKalkoken/aa-structures
Project-URL: Source, https://gitlab.com/ErikKalkoken/aa-structures
Project-URL: Tracker, https://gitlab.com/ErikKalkoken/aa-structures/-/issues
